virtual_pet/__init__.py
virtual_pet/__main__.py
virtual_pet/default_species.py
virtual_pet/default_weapons.py
virtual_pet/pet.py
virtual_pet/species.py
virtual_pet/utilities.py
virtual_pet/weapons.py
virtual_pet-1.0.0.dist-info/LICENSE
virtual_pet-1.0.0.dist-info/METADATA
virtual_pet-1.0.0.dist-info/WHEEL
virtual_pet-1.0.0.dist-info/entry_points.txt
virtual_pet-1.0.0.dist-info/top_level.txt
virtual_pet-1.0.0.dist-info/RECORD
