Metadata-Version: 2.1
Name: virtual_pet
Version: 1.0.0
Summary: A virtual pet game.
Author-email: Dhiyaa Al Jorf <da2863@nyu.edu>, Firas Darwish <fbd2014@nyu.edu>, Shubhi Upadhyay <su2132@nyu.edu>
License: GNU GENERAL PUBLIC LICENSE
Project-URL: Homepage, https://github.com/nyu-software-engineering/python-package-example
Project-URL: Repository, https://github.com/nyu-software-engineering/python-package-example.git
Project-URL: Bug Tracker, https://github.com/nyu-software-engineering/python-package-example/issues
Keywords: python,package,build,tutorial
Classifier: Programming Language :: Python :: 3
Classifier: Intended Audience :: Education
Classifier: License :: OSI Approved :: GNU General Public License v3 (GPLv3)
Classifier: Operating System :: OS Independent
Requires-Python: >=3.7
License-File: LICENSE
Requires-Dist: termcolor
Provides-Extra: dev
Requires-Dist: pytest ; extra == 'dev'
